{
  "project_info": {
    "project_number": "192933910441",
    "project_id": "assignment02-6eb11",
    "storage_bucket": "assignment02-6eb11.firebasestorage.app"
  },
  "client": [
    {
      "client_info": {
        "mobilesdk_app_id": "1:192933910441:android:0b7bacec055278810056b8",
        "android_client_info": {
          "package_name": "com.example.myapplication1"
        }
      },
      "oauth_client": [],
      "api_key": [
        {
          "current_key": "AIzaSyDNoRYcne1xHaUCJKNNto1CJHZ5Sw--jQQ"
        }
      ],
      "services": {
        "appinvite_service": {
          "other_platform_oauth_client": []
        }
      }
    }
  ],
  "configuration_version": "1"
}